tank_lab_to_nwb/__init__.py
tank_lab_to_nwb/nwbwidgets.py
tank_lab_to_nwb/towers_task_placefield.py
tank_lab_to_nwb/utils.py
tank_lab_to_nwb/convert_towers_task/__init__.py
tank_lab_to_nwb/convert_towers_task/convert_towers.py
tank_lab_to_nwb/convert_towers_task/towersnwbconverter.py
tank_lab_to_nwb/convert_towers_task/virmenbehaviordatainterface.py
tank_lab_to_nwb-0.2.0.dist-info/LICENSE
tank_lab_to_nwb-0.2.0.dist-info/METADATA
tank_lab_to_nwb-0.2.0.dist-info/WHEEL
tank_lab_to_nwb-0.2.0.dist-info/top_level.txt
tank_lab_to_nwb-0.2.0.dist-info/RECORD
