Metadata-Version: 2.1
Name: tank-lab-to-nwb
Version: 0.2.0
Summary: NWB conversion scripts and tutorials.
Home-page: https://github.com/catalystneuro/tank-lab-to-nwb
Author: Luiz Tauffer, Cody Baker Szonja Weigl, and Ben Dichter
Author-email: ben.dichter@gmail.com
License: UNKNOWN
Platform: UNKNOWN
Requires-Dist: numpy
Requires-Dist: notebook
Requires-Dist: pynwb
Requires-Dist: h5py
Requires-Dist: isodate
Requires-Dist: nwb-conversion-tools
Requires-Dist: nwbwidgets
Requires-Dist: ipywidgets
Requires-Dist: ndx-tank-metadata
